LabIFSC2/__init__.py
LabIFSC2/_arrays.py
LabIFSC2/_medida.py
LabIFSC2/_regressoes.py
LabIFSC2/_tipagem_forte.py
LabIFSC2/constantes/__init__.py
LabIFSC2/constantes/constantes.py
labifsc2-0.1.0.dist-info/LICENSE
labifsc2-0.1.0.dist-info/METADATA
labifsc2-0.1.0.dist-info/WHEEL
labifsc2-0.1.0.dist-info/RECORD
