Metadata-Version: 2.3
Name: LabIFSC2
Version: 0.1.0
Summary: Cálculos de laboratório com Python, realize propagação de incertezas e conversão de medidas automaticamente
License: GNU General Public License v3.0
Keywords: LabIFSC,montecarlo,error_propagation,unit_conversion
Author: viniciusdutra314
Author-email: dutravinisousa2@usp.br
Requires-Python: >=3.10,<4.0
Classifier: Development Status :: 5 - Production/Stable
Classifier: Intended Audience :: Developers
Classifier: Intended Audience :: Science/Research
Classifier: License :: Other/Proprietary License
Classifier: Natural Language :: Portuguese (Brazilian)
Classifier: Operating System :: OS Independent
Classifier: Programming Language :: Python :: 3
Classifier: Programming Language :: Python :: 3.10
Classifier: Programming Language :: Python :: 3.11
Classifier: Programming Language :: Python :: 3.12
Classifier: Programming Language :: Python :: 3.13
Classifier: Topic :: Scientific/Engineering
Classifier: Typing :: Typed
Requires-Dist: numpy (==2.*)
Requires-Dist: pint (>=0.24,<0.25)
Project-URL: Documentation, https://labifsc2.readthedocs.io/pt-br/latest/
Project-URL: Github, https://github.com/viniciusdutra314/LabIFSC2
Project-URL: Issue Tracker, https://github.com/viniciusdutra314/LabIFSC2/issues
